plain/README.md
plain/__main__.py
plain/assets/README.md
plain/assets/__init__.py
plain/assets/finders.py
plain/assets/preflight.py
plain/assets/storage.py
plain/assets/utils.py
plain/assets/whitenoise/__init__.py
plain/assets/whitenoise/base.py
plain/assets/whitenoise/compress.py
plain/assets/whitenoise/media_types.py
plain/assets/whitenoise/middleware.py
plain/assets/whitenoise/responders.py
plain/assets/whitenoise/storage.py
plain/assets/whitenoise/string_utils.py
plain/cli/README.md
plain/cli/__init__.py
plain/cli/cli.py
plain/cli/formatting.py
plain/cli/packages.py
plain/cli/print.py
plain/cli/startup.py
plain/csrf/README.md
plain/csrf/middleware.py
plain/csrf/views.py
plain/debug.py
plain/exceptions.py
plain/forms/README.md
plain/forms/__init__.py
plain/forms/boundfield.py
plain/forms/exceptions.py
plain/forms/fields.py
plain/forms/forms.py
plain/http/README.md
plain/http/__init__.py
plain/http/cookie.py
plain/http/multipartparser.py
plain/http/request.py
plain/http/response.py
plain/internal/__init__.py
plain/internal/files/README.md
plain/internal/files/__init__.py
plain/internal/files/base.py
plain/internal/files/locks.py
plain/internal/files/move.py
plain/internal/files/temp.py
plain/internal/files/uploadedfile.py
plain/internal/files/uploadhandler.py
plain/internal/files/utils.py
plain/internal/handlers/__init__.py
plain/internal/handlers/base.py
plain/internal/handlers/exception.py
plain/internal/handlers/wsgi.py
plain/internal/legacy/__init__.py
plain/internal/legacy/__main__.py
plain/internal/legacy/management/__init__.py
plain/internal/legacy/management/base.py
plain/internal/legacy/management/color.py
plain/internal/legacy/management/commands/__init__.py
plain/internal/legacy/management/commands/collectstatic.py
plain/internal/legacy/management/sql.py
plain/internal/legacy/management/utils.py
plain/json.py
plain/logs/README.md
plain/logs/__init__.py
plain/logs/configure.py
plain/logs/loggers.py
plain/logs/utils.py
plain/middleware/README.md
plainframework-0.1.0.dist-info/LICENSE
plainframework-0.1.0.dist-info/METADATA
plainframework-0.1.0.dist-info/WHEEL
plainframework-0.1.0.dist-info/entry_points.txt
plainframework-0.1.0.dist-info/RECORD
