Metadata-Version: 2.1
Name: plainframework
Version: 0.1.0
Summary: 
Author: Dave Gaeddert
Author-email: dave.gaeddert@dropseed.dev
Requires-Python: >=3.11,<4.0
Classifier: Programming Language :: Python :: 3
Classifier: Programming Language :: Python :: 3.11
Classifier: Programming Language :: Python :: 3.12
Requires-Dist: click (>=8.0.0)
Requires-Dist: jinja2 (>=3.1.2,<4.0.0)
Requires-Dist: python-dotenv (>=1.0.0,<2.0.0)
